core/__init__.py
core/config.py
core/constants.py
core/prompts.py
data/__init__.py
data/external/__init__.py
data/interim/__init__.py
data/processed/__init__.py
data/raw/__init__.py
data/raw/contractions_dict.json
data/raw/custom_substitutions.csv
data/raw/leftovers_dict.json
data/raw/slang_dict.json
handlers/__init__.py
handlers/custom_exceptions.py
handlers/output_generator.py
models/__init__.py
musaddiquehussainlabs/__init__.py
musaddiquehussainlabs/document_analysis/__init__.py
musaddiquehussainlabs/document_analysis/document_analysis.py
musaddiquehussainlabs/nlp_components/__init__.py
musaddiquehussainlabs/nlp_components/nlp_model.py
musaddiquehussainlabs/text_preprocessing/__init__.py
musaddiquehussainlabs/text_preprocessing/contractions.py
musaddiquehussainlabs/text_preprocessing/emo_unicode.py
musaddiquehussainlabs/text_preprocessing/operations.py
musaddiquehussainlabs/text_preprocessing/slang_text.py
musaddiquehussainlabs/text_preprocessing/text_preprocessing.py
services/__init__.py
services/langchain_framework.py
services/spacy_extractor.py
musaddiquehussainlabs-0.0.2.dist-info/LICENSE
musaddiquehussainlabs-0.0.2.dist-info/METADATA
musaddiquehussainlabs-0.0.2.dist-info/WHEEL
musaddiquehussainlabs-0.0.2.dist-info/top_level.txt
musaddiquehussainlabs-0.0.2.dist-info/RECORD
