Metadata-Version: 2.1
Name: musaddiquehussainlabs
Version: 0.0.2
Summary: MusaddiqueHussainLabs: Empowering text analytics with advanced tools for comprehensive Natural Language Processing (NLP) and Language Models (LLMs).
Author-email: MusaddiqueHussain Jahagirdar <musaddiquehussainlabs@gmail.com>
Maintainer-email: MusaddiqueHussain Jahagirdar <musaddiquehussainlabs@gmail.com>
Project-URL: Homepage, https://demo-musaddiquehussainlabs.streamlit.app/
Project-URL: Documentation, https://musaddiquehussainlabs.github.io/musaddiquehussainlabs_package/
Project-URL: Repository, https://github.com/MusaddiqueHussainLabs/musaddiquehussainlabs_package.git
Project-URL: Issues, https://github.com/MusaddiqueHussainLabs/musaddiquehussainlabs_package/issues
Project-URL: Changelog, https://github.com/MusaddiqueHussainLabs/musaddiquehussainlabs_package/blob/main/CHANGELOG.md
Keywords: nlp,llm,text preprocessing,document analysis,langchain,google gemini
Classifier: Development Status :: 3 - Alpha
Classifier: Intended Audience :: Developers
Classifier: Topic :: Scientific/Engineering :: Artificial Intelligence
Classifier: License :: OSI Approved :: MIT License
Classifier: Operating System :: OS Independent
Classifier: Intended Audience :: Developers
Classifier: Programming Language :: Python :: 3
Classifier: Programming Language :: Python :: 3.9
Classifier: Programming Language :: Python :: 3.10
Classifier: Programming Language :: Python :: 3.11
Requires-Python: >=3.9
License-File: LICENSE
Requires-Dist: langchain ==0.0.350
Requires-Dist: langchain-google-genai
Requires-Dist: langchain-experimental
Requires-Dist: spacy ==3.7.2
Requires-Dist: pydantic-settings ==2.1.0
Requires-Dist: presidio-analyzer
Requires-Dist: presidio-anonymizer
Requires-Dist: Faker
Requires-Dist: regex
Requires-Dist: beautifulsoup4
Requires-Dist: html5lib
Requires-Dist: lxml
Requires-Dist: nltk
Requires-Dist: textsearch
